{"date": "2020-02-14", "view_date": "2020-02-17", "rows": [{"product": "台指期", "day_lots": -3887, "day_cost": 11807.030295233808, "close_price": 11812, "oi_lots": 41002, "oi_cost": 11811.728940051706, "night_lots": 0, "night_cost": null, "pre_open_lots": 41002, "pre_open_cp": null}, {"product": "電子期", "day_lots": -12, "day_cost": 538.875, "close_price": 523.6, "oi_lots": 988, "oi_cost": 523.1308198380567, "night_lots": 0, "night_cost": null, "pre_open_lots": null, "pre_open_cp": null}, {"product": "金融期", "day_lots": -2, "day_cost": 1275.0, "close_price": 1364.6, "oi_lots": -1064, "oi_cost": 1363.686090225564, "night_lots": null, "night_cost": null, "pre_open_lots": null, "pre_open_cp": null}, {"product": "買權CALL", "day_lots": 682, "day_cost": -163.98826979472142, "close_price": null, "oi_lots": 1580, "oi_cost": 1095.2151898734178, "night_lots": 0, "night_cost": null, "pre_open_lots": 1580, "pre_open_cp": 41880}, {"product": "賣權PUT", "day_lots": 526, "day_cost": -336.46387832699617, "close_price": null, "oi_lots": -40300, "oi_cost": 38.552357320099254, "night_lots": 0, "night_cost": null, "pre_open_lots": -40300, "pre_open_cp": 41880}, {"product": "股票期貨", "day_lots": 0, "day_cost": null, "close_price": null, "oi_lots": 0, "oi_cost": null, "night_lots": null, "night_cost": null, "pre_open_lots": null, "pre_open_cp": null}], "tx_close": 11812, "twii_close": 11815.7, "margin": {"twse_margin_amt_oku": 1326.3459, "tpex_margin_amt_oku": 492.1163, "twse_mkt_cap_chao": 35.876831, "tpex_mkt_cap_chao": 3.3956, "twse_margin_pct": 0.003696942742796876, "tpex_margin_pct": 0.014492764165390507, "mkt_cap_source": "interp"}, "last_refresh": {"id": 898, "ts": "2026-06-23T10:17:28", "target_date": "2026-06-23", "ok": 1, "errors_json": "[]"}}