{"date": "2020-02-10", "view_date": "2020-02-11", "rows": [{"product": "台指期", "day_lots": -408, "day_cost": 11669.484662576688, "close_price": 11564, "oi_lots": 37804, "oi_cost": 11571.907788145512, "night_lots": 0, "night_cost": null, "pre_open_lots": 37804, "pre_open_cp": null}, {"product": "電子期", "day_lots": 96, "day_cost": 515.9583333333334, "close_price": 508.55, "oi_lots": 1086, "oi_cost": 508.45971454880294, "night_lots": 0, "night_cost": null, "pre_open_lots": null, "pre_open_cp": null}, {"product": "金融期", "day_lots": -57, "day_cost": 1361.280701754386, "close_price": 1352.8, "oi_lots": -1094, "oi_cost": 1351.9140767824497, "night_lots": null, "night_cost": null, "pre_open_lots": null, "pre_open_cp": null}, {"product": "買權CALL", "day_lots": -10322, "day_cost": 29.120325518310402, "close_price": null, "oi_lots": -14341, "oi_cost": -68.87525277177323, "night_lots": 0, "night_cost": null, "pre_open_lots": -14341, "pre_open_cp": 18163}, {"product": "賣權PUT", "day_lots": 1462, "day_cost": 347.9343365253078, "close_price": null, "oi_lots": -32504, "oi_cost": 47.60460251046025, "night_lots": 0, "night_cost": null, "pre_open_lots": -32504, "pre_open_cp": 18163}, {"product": "股票期貨", "day_lots": 0, "day_cost": null, "close_price": null, "oi_lots": 0, "oi_cost": null, "night_lots": null, "night_cost": null, "pre_open_lots": null, "pre_open_cp": null}], "tx_close": 11564, "twii_close": 11574.07, "margin": {"twse_margin_amt_oku": 1319.43067, "tpex_margin_amt_oku": 488.59883, "twse_mkt_cap_chao": 35.143153039783506, "tpex_mkt_cap_chao": 3.263278, "twse_margin_pct": 0.003754445904459255, "tpex_margin_pct": 0.014972638861905115, "mkt_cap_source": "interp"}, "last_refresh": {"id": 898, "ts": "2026-06-23T10:17:28", "target_date": "2026-06-23", "ok": 1, "errors_json": "[]"}}