{"date": "2020-02-04", "view_date": "2020-02-05", "rows": [{"product": "台指期", "day_lots": 5256, "day_cost": 11490.111771700356, "close_price": 11534, "oi_lots": 37696, "oi_cost": 11540.505222668036, "night_lots": 0, "night_cost": null, "pre_open_lots": 37696, "pre_open_cp": null}, {"product": "電子期", "day_lots": 50, "day_cost": 513.19, "close_price": 508.3, "oi_lots": 542, "oi_cost": 508.02260147601476, "night_lots": 0, "night_cost": null, "pre_open_lots": null, "pre_open_cp": null}, {"product": "金融期", "day_lots": 129, "day_cost": 1338.4186046511627, "close_price": 1340.4, "oi_lots": -1040, "oi_cost": 1340.0028846153846, "night_lots": null, "night_cost": null, "pre_open_lots": null, "pre_open_cp": null}, {"product": "買權CALL", "day_lots": 28072, "day_cost": 53.405528640638366, "close_price": null, "oi_lots": -16348, "oi_cost": -96.97822363591877, "night_lots": 0, "night_cost": null, "pre_open_lots": -16348, "pre_open_cp": 6005}, {"product": "賣權PUT", "day_lots": -1352, "day_cost": 380.01479289940823, "close_price": null, "oi_lots": -22353, "oi_cost": -0.06173667964031674, "night_lots": 0, "night_cost": null, "pre_open_lots": -22353, "pre_open_cp": 6005}, {"product": "股票期貨", "day_lots": 0, "day_cost": null, "close_price": null, "oi_lots": 0, "oi_cost": null, "night_lots": null, "night_cost": null, "pre_open_lots": null, "pre_open_cp": null}], "tx_close": 11534, "twii_close": 11555.92, "margin": {"twse_margin_amt_oku": 1321.06707, "tpex_margin_amt_oku": 492.6354, "twse_mkt_cap_chao": 35.08715829472453, "tpex_mkt_cap_chao": 3.270058, "twse_margin_pct": 0.0037651013482007368, "tpex_margin_pct": 0.015065035543712068, "mkt_cap_source": "interp"}}