{"date": "2021-07-30", "view_date": "2021-08-02", "rows": [{"product": "台指期", "day_lots": -1934, "day_cost": 17329.06670113754, "close_price": 17173, "oi_lots": -17144, "oi_cost": 17153.08075947152, "night_lots": 0, "night_cost": null, "pre_open_lots": -17144, "pre_open_cp": null}, {"product": "電子期", "day_lots": 72, "day_cost": 820.1631944444445, "close_price": 817.4, "oi_lots": 230, "oi_cost": 817.5510869565218, "night_lots": 0, "night_cost": null, "pre_open_lots": null, "pre_open_cp": null}, {"product": "金融期", "day_lots": 73, "day_cost": 1504.4794520547946, "close_price": 1506.4, "oi_lots": -1530, "oi_cost": 1506.8692810457517, "night_lots": null, "night_cost": null, "pre_open_lots": null, "pre_open_cp": null}, {"product": "買權CALL", "day_lots": 560, "day_cost": -997.6785714285713, "close_price": null, "oi_lots": -5420, "oi_cost": 653.6051660516605, "night_lots": 0, "night_cost": null, "pre_open_lots": -5420, "pre_open_cp": -23333}, {"product": "賣權PUT", "day_lots": -557, "day_cost": -802.4057450628367, "close_price": null, "oi_lots": 17913, "oi_cost": 6.280355049405459, "night_lots": 0, "night_cost": null, "pre_open_lots": 17913, "pre_open_cp": -23333}, {"product": "股票期貨", "day_lots": 0, "day_cost": null, "close_price": null, "oi_lots": 0, "oi_cost": null, "night_lots": null, "night_cost": null, "pre_open_lots": null, "pre_open_cp": null}], "tx_close": 17173, "twii_close": 17247.41, "margin": {"twse_margin_amt_oku": 2914.66562, "tpex_margin_amt_oku": 726.71473, "twse_mkt_cap_chao": 52.893641, "tpex_mkt_cap_chao": 5.248897, "twse_margin_pct": 0.005510427274235102, "tpex_margin_pct": 0.013845094121679278, "mkt_cap_source": "interp"}}