{"date": "2021-04-01", "view_date": "2021-04-06", "rows": [{"product": "台指期", "day_lots": 2866, "day_cost": 16501.65038381019, "close_price": 16551, "oi_lots": 3720, "oi_cost": 16662.41516027149, "night_lots": 0, "night_cost": null, "pre_open_lots": 3720, "pre_open_cp": null}, {"product": "電子期", "day_lots": 27, "day_cost": 824.3333333333334, "close_price": 831.45, "oi_lots": 227, "oi_cost": 830.9306167400881, "night_lots": 0, "night_cost": null, "pre_open_lots": null, "pre_open_cp": null}, {"product": "金融期", "day_lots": 127, "day_cost": 1390.0629921259842, "close_price": 1388.4, "oi_lots": -1167, "oi_cost": 1387.8003427592116, "night_lots": null, "night_cost": null, "pre_open_lots": null, "pre_open_cp": null}, {"product": "買權CALL", "day_lots": 4954, "day_cost": -29.697214372224465, "close_price": null, "oi_lots": 9436, "oi_cost": -129.69902501059772, "night_lots": 0, "night_cost": null, "pre_open_lots": 9436, "pre_open_cp": -8377}, {"product": "賣權PUT", "day_lots": 2389, "day_cost": -127.03223105902052, "close_price": null, "oi_lots": 17813, "oi_cost": -7.154325492617751, "night_lots": 0, "night_cost": null, "pre_open_lots": 17813, "pre_open_cp": -8377}, {"product": "股票期貨", "day_lots": 0, "day_cost": null, "close_price": null, "oi_lots": 0, "oi_cost": null, "night_lots": null, "night_cost": null, "pre_open_lots": null, "pre_open_cp": null}], "tx_close": 16551, "twii_close": 16571.28, "margin": {"twse_margin_amt_oku": 2328.12929, "tpex_margin_amt_oku": 713.26914, "twse_mkt_cap_chao": 50.579727, "tpex_mkt_cap_chao": 4.943676, "twse_margin_pct": 0.004602890185627139, "tpex_margin_pct": 0.014427910324220276, "mkt_cap_source": "interp"}, "last_refresh": {"id": 900, "ts": "2026-06-23T03:22:42", "target_date": "2026-06-23", "ok": 1, "errors_json": "[]"}}