{"date": "2023-10-18", "view_date": "2023-10-19", "rows": [{"product": "台指期", "day_lots": -10092, "day_cost": 16547.255115691423, "close_price": 16426, "oi_lots": -13356, "oi_cost": 16466.916496640024, "night_lots": -1460, "night_cost": 16423.143297380586, "pre_open_lots": -14816, "pre_open_cp": null}, {"product": "電子期", "day_lots": -203, "day_cost": 813.2041949413942, "close_price": 806.2, "oi_lots": -380, "oi_cost": 806.6489151873767, "night_lots": -33, "night_cost": 804.1679389312977, "pre_open_lots": null, "pre_open_cp": null}, {"product": "金融期", "day_lots": 68, "day_cost": 1643.7226277372263, "close_price": 1642.4, "oi_lots": -64, "oi_cost": 1648.390625, "night_lots": null, "night_cost": null, "pre_open_lots": null, "pre_open_cp": null}, {"product": "買權CALL", "day_lots": -40965, "day_cost": 30.85170267301355, "close_price": null, "oi_lots": 19427, "oi_cost": 209.97786585679722, "night_lots": 1586, "night_cost": -74.72887767969735, "pre_open_lots": 21013, "pre_open_cp": -9088}, {"product": "賣權PUT", "day_lots": 14415, "day_cost": 51.45750953867499, "close_price": null, "oi_lots": 27586, "oi_cost": 143.19582396867978, "night_lots": 2515, "night_cost": 19.332007952286283, "pre_open_lots": 30101, "pre_open_cp": -9088}, {"product": "股票期貨", "day_lots": 2075, "day_cost": -98.40385542168674, "close_price": null, "oi_lots": -177276, "oi_cost": 107.9747230307543, "night_lots": null, "night_cost": null, "pre_open_lots": null, "pre_open_cp": null}], "tx_close": 16426, "twii_close": 16440.91, "margin": {"twse_margin_amt_oku": 2257.36952, "tpex_margin_amt_oku": 814.05625, "twse_mkt_cap_chao": 51.82430890959155, "tpex_mkt_cap_chao": 5.292624, "twse_margin_pct": 0.004355812103424326, "tpex_margin_pct": 0.015380957536375152, "mkt_cap_source": "interp"}, "last_refresh": {"id": 900, "ts": "2026-06-23T03:22:42", "target_date": "2026-06-23", "ok": 1, "errors_json": "[]"}}