{"date": "2024-05-15", "view_date": "2024-05-16", "rows": [{"product": "台指期", "day_lots": 539, "day_cost": 21114.99304589708, "close_price": 21143, "oi_lots": -9945, "oi_cost": 21217.421884819385, "night_lots": -2216, "night_cost": 21328.775095871868, "pre_open_lots": -12162, "pre_open_cp": null}, {"product": "電子期", "day_lots": -48, "day_cost": 1103.4240837696334, "close_price": 1103.3, "oi_lots": -140, "oi_cost": 1110.4986595174262, "night_lots": -27, "night_cost": 1117.2811059907833, "pre_open_lots": null, "pre_open_cp": null}, {"product": "金融期", "day_lots": 89, "day_cost": 1946.3211267605634, "close_price": 1949.4, "oi_lots": -454, "oi_cost": 1956.2491730981258, "night_lots": null, "night_cost": null, "pre_open_lots": null, "pre_open_cp": null}, {"product": "買權CALL", "day_lots": -1645, "day_cost": -66.26139817629179, "close_price": null, "oi_lots": 23141, "oi_cost": 535.7745991962317, "night_lots": 967, "night_cost": -1016.8562564632886, "pre_open_lots": 24108, "pre_open_cp": 10510}, {"product": "賣權PUT", "day_lots": -37186, "day_cost": 17.854568923788523, "close_price": null, "oi_lots": 9388, "oi_cost": 45.29399233063486, "night_lots": 4210, "night_cost": 29.672209026128264, "pre_open_lots": 13598, "pre_open_cp": 10510}, {"product": "股票期貨", "day_lots": -5915, "day_cost": 192.74184277261202, "close_price": null, "oi_lots": -283185, "oi_cost": 143.65031869625864, "night_lots": null, "night_cost": null, "pre_open_lots": null, "pre_open_cp": null}], "tx_close": 21143, "twii_close": 21147.21, "margin": {"twse_margin_amt_oku": 2896.42159, "tpex_margin_amt_oku": 1037.89109, "twse_mkt_cap_chao": 67.2952761424745, "tpex_mkt_cap_chao": 6.14522, "twse_margin_pct": 0.004304048896192695, "tpex_margin_pct": 0.016889404935868855, "mkt_cap_source": "interp"}}