{"date": "2024-12-17", "view_date": "2024-12-18", "rows": [{"product": "台指期", "day_lots": 891, "day_cost": 22405.89027263548, "close_price": 23031, "oi_lots": -43088, "oi_cost": 23082.83855305925, "night_lots": 2669, "night_cost": 22937.282895846216, "pre_open_lots": -40420, "pre_open_cp": null}, {"product": "電子期", "day_lots": 8, "day_cost": 1257.6825396825398, "close_price": 1277.8, "oi_lots": -518, "oi_cost": 1278.9782608695652, "night_lots": -14, "night_cost": 1275.5652173913043, "pre_open_lots": null, "pre_open_cp": null}, {"product": "金融期", "day_lots": -44, "day_cost": 2148.681818181818, "close_price": 2128.8, "oi_lots": -278, "oi_cost": 2130.546762589928, "night_lots": null, "night_cost": null, "pre_open_lots": null, "pre_open_cp": null}, {"product": "買權CALL", "day_lots": 9118, "day_cost": -5.597718797982013, "close_price": null, "oi_lots": 14196, "oi_cost": 320.86080586080584, "night_lots": -5213, "night_cost": -15.323230385574524, "pre_open_lots": 8983, "pre_open_cp": 12238}, {"product": "賣權PUT", "day_lots": -7004, "day_cost": 94.11479154768705, "close_price": null, "oi_lots": -2361, "oi_cost": -1427.0902160101652, "night_lots": -894, "night_cost": -377.5167785234899, "pre_open_lots": -3255, "pre_open_cp": 12238}, {"product": "股票期貨", "day_lots": 3560, "day_cost": 172.16264044943821, "close_price": null, "oi_lots": -308991, "oi_cost": 150.30532766326527, "night_lots": null, "night_cost": null, "pre_open_lots": null, "pre_open_cp": null}], "tx_close": 23031, "twii_close": 23018.01, "margin": {"twse_margin_amt_oku": 3208.85324, "tpex_margin_amt_oku": 1149.19397, "twse_mkt_cap_chao": 73.85858180158684, "tpex_mkt_cap_chao": 6.474763, "twse_margin_pct": 0.00434459092190565, "tpex_margin_pct": 0.01774881906874429, "mkt_cap_source": "interp"}, "last_refresh": {"id": 898, "ts": "2026-06-23T10:17:28", "target_date": "2026-06-23", "ok": 1, "errors_json": "[]"}}