{"date": "2025-03-03", "view_date": "2025-03-04", "rows": [{"product": "台指期", "day_lots": -9538, "day_cost": 22764.076514591557, "close_price": 22718, "oi_lots": -49869, "oi_cost": 22723.192032701776, "night_lots": 2219, "night_cost": 22489.956745066233, "pre_open_lots": -47649, "pre_open_cp": null}, {"product": "電子期", "day_lots": -64, "day_cost": 1236.21484375, "close_price": 1230.8, "oi_lots": -471, "oi_cost": 1232.1434262948208, "night_lots": -28, "night_cost": 1217.7857142857142, "pre_open_lots": null, "pre_open_cp": null}, {"product": "金融期", "day_lots": 28, "day_cost": 2179.754385964912, "close_price": 2181, "oi_lots": -147, "oi_cost": 2180.5996592844976, "night_lots": null, "night_cost": null, "pre_open_lots": null, "pre_open_cp": null}, {"product": "買權CALL", "day_lots": -13970, "day_cost": 89.29277022190408, "close_price": null, "oi_lots": 12698, "oi_cost": 341.45692234997637, "night_lots": -2507, "night_cost": 111.2564818508177, "pre_open_lots": 10191, "pre_open_cp": -9697}, {"product": "賣權PUT", "day_lots": 5190, "day_cost": 400.78612716763007, "close_price": null, "oi_lots": 23659, "oi_cost": 273.9540978063316, "night_lots": -3771, "night_cost": 16.870856536727658, "pre_open_lots": 19888, "pre_open_cp": -9697}, {"product": "股票期貨", "day_lots": -568, "day_cost": -390.61531690140845, "close_price": null, "oi_lots": -342677, "oi_cost": 142.96539014874065, "night_lots": null, "night_cost": null, "pre_open_lots": null, "pre_open_cp": null}], "tx_close": 22718, "twii_close": 22756.25, "margin": {"twse_margin_amt_oku": 3240.50396, "tpex_margin_amt_oku": 1144.55517, "twse_mkt_cap_chao": 73.14327765583204, "tpex_mkt_cap_chao": 6.677547, "twse_margin_pct": 0.004430351036834648, "tpex_margin_pct": 0.017140353635848614, "mkt_cap_source": "interp"}, "last_refresh": {"id": 898, "ts": "2026-06-23T10:17:28", "target_date": "2026-06-23", "ok": 1, "errors_json": "[]"}}