{"date": "2026-07-13", "view_date": "2026-07-14", "rows": [{"product": "台指期", "day_lots": -302, "day_cost": 90715.37190082645, "close_price": 45617, "oi_lots": -81909, "oi_cost": 45806.934040785534, "night_lots": 0, "night_cost": null, "pre_open_lots": -81909, "pre_open_cp": null}, {"product": "電子期", "day_lots": 4, "day_cost": 1674.625, "close_price": 2929.9, "oi_lots": -408, "oi_cost": 2933.6200980392155, "night_lots": 0, "night_cost": null, "pre_open_lots": null, "pre_open_cp": null}, {"product": "金融期", "day_lots": -23, "day_cost": 3080.2150537634407, "close_price": 3130.8, "oi_lots": -215, "oi_cost": 3130.5226480836236, "night_lots": null, "night_cost": null, "pre_open_lots": null, "pre_open_cp": null}, {"product": "買權CALL", "day_lots": -2047, "day_cost": -595.8085002442599, "close_price": null, "oi_lots": 8164, "oi_cost": -482.9397354238119, "night_lots": 0, "night_cost": null, "pre_open_lots": 8164, "pre_open_cp": -1814}, {"product": "賣權PUT", "day_lots": -3217, "day_cost": 117.61268262356232, "close_price": null, "oi_lots": 9978, "oi_cost": 120.96812988574865, "night_lots": 0, "night_cost": null, "pre_open_lots": 9978, "pre_open_cp": -1814}, {"product": "股票期貨", "day_lots": 19912, "day_cost": 146.8602601446364, "close_price": null, "oi_lots": -801298, "oi_cost": 287.724511355326, "night_lots": null, "night_cost": null, "pre_open_lots": null, "pre_open_cp": null}], "tx_close": 45617, "twii_close": 45380.52, "margin": {"twse_margin_amt_oku": null, "tpex_margin_amt_oku": null, "twse_mkt_cap_chao": 148.00071813679838, "tpex_mkt_cap_chao": null, "twse_margin_pct": null, "tpex_margin_pct": null, "mkt_cap_source": "interp"}}